README.md
setup.cfg
setup.py
qsy/__init__.py
qsy/classical_register.py
qsy/quantum_register.py
qsy/register.py
qsy/util.py
qsy.egg-info/PKG-INFO
qsy.egg-info/SOURCES.txt
qsy.egg-info/dependency_links.txt
qsy.egg-info/entry_points.txt
qsy.egg-info/requires.txt
qsy.egg-info/top_level.txt
qsy/backends/__init__.py
qsy/backends/backend.py
qsy/backends/chp.py
qsy/backends/statevector.py
qsy/gates/__init__.py
qsy/gates/clifford.py
qsy/gates/gate.py
qsy/gates/non_clifford.py
qsy/gates/pauli.py
qsyasm/cli.py
qsyasm/env.py
qsyasm/error.py
qsyasm/instruction.py
qsyasm/log.py
qsyasm/program.py