Metadata-Version: 2.1
Name: qsy
Version: 0.4.4
Summary: A quantum computer state vector/stabilizer circuit simulator and assembly language
Home-page: https://github.com/soudy/qsy
Author: Steven Oud
Author-email: soud@pm.me
License: MIT
Download-URL: https://github.com/soudy/qsy/archive/v0.4.4.tar.gz
Keywords: quantum,computing,simulator,stabilizer,circuit,assembly,chp,statevector
Platform: UNKNOWN
Classifier: Environment :: Console
Classifier: License :: OSI Approved :: MIT License
Classifier: Operating System :: OS Independent
Classifier: Programming Language :: Python :: 3 :: Only
Classifier: Topic :: Software Development :: Assemblers
